bbndb/__init__.py
bbndb/auspex.py
bbndb/calibration.py
bbndb/qgl.py
bbndb/session.py
bbndb-2020.1.dist-info/LICENSE
bbndb-2020.1.dist-info/METADATA
bbndb-2020.1.dist-info/WHEEL
bbndb-2020.1.dist-info/top_level.txt
bbndb-2020.1.dist-info/RECORD
