Metadata-Version: 2.1
Name: bbndb
Version: 2020.1
Summary: BBN Configuration Database
Home-page: https://github.com/BBN-Q/bbndb
Author: Graham Rowlands
License: Apache 2.0 License
Download-URL: https://github.com/BBN-Q/bbndb
Keywords: quantum qubit instrument experiment control database configuration
Platform: UNKNOWN
Classifier: Development Status :: 4 - Beta
Classifier: Intended Audience :: Science/Research
Classifier: License :: OSI Approved :: Apache Software License
Classifier: Operating System :: MacOS
Classifier: Operating System :: POSIX
Classifier: Programming Language :: Python :: 3 :: Only
Classifier: Programming Language :: Python :: 3.6
Classifier: Programming Language :: Python :: 3.7
Classifier: Topic :: Scientific/Engineering
Requires-Python: >=3.6
Requires-Dist: sqlalchemy (>=1.2.15)
Requires-Dist: numpy (>=1.12.1)
Requires-Dist: networkx (>=1.11)
Requires-Dist: alembic
